eagle_downloader/__init__.py
eagle_downloader/main.py
eagle_downloader/tests/__init__.py
eagle_downloader/tests/main.py
eagle_downloader-1.0.2.1.dist-info/LICENSE
eagle_downloader-1.0.2.1.dist-info/METADATA
eagle_downloader-1.0.2.1.dist-info/WHEEL
eagle_downloader-1.0.2.1.dist-info/entry_points.txt
eagle_downloader-1.0.2.1.dist-info/top_level.txt
eagle_downloader-1.0.2.1.dist-info/RECORD
