Metadata-Version: 2.1
Name: eagle-downloader
Version: 1.0.2.1
Summary: A CLI tool to download media from YouTube.
Home-page: https://github.com/gfrancodev/eagle-downloader
Author: Gustavo Franco
Author-email: contact@gfrancodev.com
Classifier: Programming Language :: Python :: 3
Classifier: License :: OSI Approved :: MIT License
Classifier: Operating System :: OS Independent
License-File: LICENSE
Requires-Dist: yt-dlp==2023.9.24
Requires-Dist: questionary==1.10.0
Requires-Dist: tqdm==4.66.1
Requires-Dist: colorama==0.4.6
